{
  "books": [
    {
      "title": "Whisper of wind",
      "id": "Yi5xEFvco",
      "description": "",
      "coverUrl": "http://res.cloudinary.com/dccylqden/image/upload/v1600636453/qjtf9hn8tt45ioufbqym.jpg"
    },
    {
      "title": "Thinking, fast and slow",
      "id": "ZQnh2SCCn"
    },
    {
      "title": "Alone Walker",
      "id": "Gb5j6TLyk",
      "coverUrl": "http://res.cloudinary.com/dccylqden/image/upload/v1598840577/nob1rd5m0haatkqfayze.jpg"
    }
  ],
  "users": [
    {
      "name": "Van",
      "email": "vanmiu170797@gmail.com",
      "phone": "0969557603",
      "id": "vQwbCqEBl",
      "password": "$2b$10$l9lc0mXS/K.XXto29mWW4OLaTwJuwbnwGkL7dHd35J2rQVk/qjr66",
      "isAdmin": true,
      "wrongLoginCount": 0,
      "avatarUrl": "http://res.cloudinary.com/dccylqden/image/upload/v1598729447/up5wtmoz6clztn5pbwvo.jpg"
    },
    {
      "name": "Nga",
      "email": "thuyvannguyen97.bk@gmail.com",
      "phone": "0987654321",
      "id": "81fugC_nl",
      "password": "$2b$10$l9lc0mXS/K.XXto29mWW4OLaTwJuwbnwGkL7dHd35J2rQVk/qjr66",
      "isAdmin": false,
      "wrongLoginCount": 0
    },
    {
      "name": "Ngan",
      "email": "hien2@gmail.com",
      "phone": "0987654321",
      "id": "RSpOpAkTn",
      "password": "$2b$10$l9lc0mXS/K.XXto29mWW4OLaTwJuwbnwGkL7dHd35J2rQVk/qjr66",
      "isAdmin": false,
      "wrongLoginCount": 0
    },
    {
      "id": 1,
      "name": "Jareb",
      "email": "jparman0@youtu.be",
      "phone": "250-549-1704",
      "password": "$2b$10$l9lc0mXS/K.XXto29mWW4OLaTwJuwbnwGkL7dHd35J2rQVk/qjr66"
    },
    {
      "id": 2,
      "name": "Eadie",
      "email": "eaiskovitch1@linkedin.com",
      "phone": "205-192-0711",
      "password": "$2b$10$l9lc0mXS/K.XXto29mWW4OLaTwJuwbnwGkL7dHd35J2rQVk/qjr66"
    },
    {
      "id": 3,
      "name": "Tymothy",
      "email": "tstansfield2@senate.gov",
      "phone": "504-243-2023",
      "password": "$2b$10$l9lc0mXS/K.XXto29mWW4OLaTwJuwbnwGkL7dHd35J2rQVk/qjr66"
    },
    {
      "id": 4,
      "name": "Matty",
      "email": "mmccuish3@cbsnews.com",
      "phone": "362-984-6449",
      "password": "$2b$10$l9lc0mXS/K.XXto29mWW4OLaTwJuwbnwGkL7dHd35J2rQVk/qjr66"
    },
    {
      "id": 5,
      "name": "Gaylene",
      "email": "gblanchette4@irs.gov",
      "phone": "576-839-0906",
      "password": "$2b$10$l9lc0mXS/K.XXto29mWW4OLaTwJuwbnwGkL7dHd35J2rQVk/qjr66"
    },
    {
      "id": 6,
      "name": "Fayette",
      "email": "fnevison5@ox.ac.uk",
      "phone": "773-750-1580",
      "password": "$2b$10$l9lc0mXS/K.XXto29mWW4OLaTwJuwbnwGkL7dHd35J2rQVk/qjr66"
    },
    {
      "id": 7,
      "name": "Barby",
      "email": "byurin6@cornell.edu",
      "phone": "268-373-0859",
      "password": "$2b$10$l9lc0mXS/K.XXto29mWW4OLaTwJuwbnwGkL7dHd35J2rQVk/qjr66"
    },
    {
      "id": 8,
      "name": "Jeromy",
      "email": "jonn7@fc2.com",
      "phone": "694-445-8617",
      "password": "$2b$10$l9lc0mXS/K.XXto29mWW4OLaTwJuwbnwGkL7dHd35J2rQVk/qjr66"
    },
    {
      "id": 9,
      "name": "Aridatha",
      "email": "ajinda8@hc360.com",
      "phone": "698-324-4905",
      "password": "$2b$10$l9lc0mXS/K.XXto29mWW4OLaTwJuwbnwGkL7dHd35J2rQVk/qjr66"
    },
    {
      "id": 10,
      "name": "Cordula",
      "email": "cottley9@guardian.co.uk",
      "phone": "417-319-6997",
      "password": "$2b$10$l9lc0mXS/K.XXto29mWW4OLaTwJuwbnwGkL7dHd35J2rQVk/qjr66"
    },
    {
      "id": 11,
      "name": "Any",
      "email": "aespinosa@statcounter.com",
      "phone": "401-731-5488",
      "password": "$2b$10$l9lc0mXS/K.XXto29mWW4OLaTwJuwbnwGkL7dHd35J2rQVk/qjr66"
    },
    {
      "id": 12,
      "name": "Cazzie",
      "email": "cissonb@yahoo.com",
      "phone": "875-594-7493",
      "password": "$2b$10$l9lc0mXS/K.XXto29mWW4OLaTwJuwbnwGkL7dHd35J2rQVk/qjr66"
    },
    {
      "id": 13,
      "name": "Jodi",
      "email": "jhoulistonc@usa.gov",
      "phone": "679-348-5473",
      "password": "$2b$10$l9lc0mXS/K.XXto29mWW4OLaTwJuwbnwGkL7dHd35J2rQVk/qjr66"
    },
    {
      "id": 14,
      "name": "Corby",
      "email": "chenstoned@photobucket.com",
      "phone": "795-176-9515",
      "password": "$2b$10$l9lc0mXS/K.XXto29mWW4OLaTwJuwbnwGkL7dHd35J2rQVk/qjr66"
    },
    {
      "id": 15,
      "name": "Muhammad",
      "email": "mkettlestringee@mapquest.com",
      "phone": "384-352-6783",
      "password": "$2b$10$l9lc0mXS/K.XXto29mWW4OLaTwJuwbnwGkL7dHd35J2rQVk/qjr66"
    },
    {
      "id": 16,
      "name": "Chauncey",
      "email": "cmynottf@huffingtonpost.com",
      "phone": "915-559-2858",
      "password": "$2b$10$l9lc0mXS/K.XXto29mWW4OLaTwJuwbnwGkL7dHd35J2rQVk/qjr66"
    },
    {
      "id": 17,
      "name": "Norah",
      "email": "nantonichg@patch.com",
      "phone": "985-726-7952",
      "password": "$2b$10$l9lc0mXS/K.XXto29mWW4OLaTwJuwbnwGkL7dHd35J2rQVk/qjr66"
    },
    {
      "id": 18,
      "name": "Hyacinthia",
      "email": "hraundsh@loc.gov",
      "phone": "285-825-2172",
      "password": "$2b$10$l9lc0mXS/K.XXto29mWW4OLaTwJuwbnwGkL7dHd35J2rQVk/qjr66"
    },
    {
      "id": 19,
      "name": "Maria",
      "email": "mbrentoni@sciencedaily.com",
      "phone": "608-790-5527",
      "password": "$2b$10$l9lc0mXS/K.XXto29mWW4OLaTwJuwbnwGkL7dHd35J2rQVk/qjr66"
    },
    {
      "id": 20,
      "name": "Giovanni",
      "email": "gdemerj@i2i.jp",
      "phone": "717-736-1865",
      "password": "$2b$10$l9lc0mXS/K.XXto29mWW4OLaTwJuwbnwGkL7dHd35J2rQVk/qjr66"
    },
    {
      "id": 21,
      "name": "Skippy",
      "email": "shalcrok@csmonitor.com",
      "phone": "945-954-6346",
      "password": "$2b$10$l9lc0mXS/K.XXto29mWW4OLaTwJuwbnwGkL7dHd35J2rQVk/qjr66"
    },
    {
      "id": 22,
      "name": "Gillan",
      "email": "gvonbrookl@spiegel.de",
      "phone": "246-276-5218",
      "password": "$2b$10$l9lc0mXS/K.XXto29mWW4OLaTwJuwbnwGkL7dHd35J2rQVk/qjr66"
    },
    {
      "id": 23,
      "name": "Catie",
      "email": "cbrocketm@army.mil",
      "phone": "446-716-1886",
      "password": "$2b$10$l9lc0mXS/K.XXto29mWW4OLaTwJuwbnwGkL7dHd35J2rQVk/qjr66"
    },
    {
      "id": 24,
      "name": "Van",
      "email": "vcourceyn@netvibes.com",
      "phone": "454-611-5039",
      "password": "$2b$10$l9lc0mXS/K.XXto29mWW4OLaTwJuwbnwGkL7dHd35J2rQVk/qjr66"
    },
    {
      "id": 25,
      "name": "Trevor",
      "email": "tiannettio@naver.com",
      "phone": "796-107-6829",
      "password": "$2b$10$l9lc0mXS/K.XXto29mWW4OLaTwJuwbnwGkL7dHd35J2rQVk/qjr66"
    },
    {
      "id": 26,
      "name": "Brigida",
      "email": "bbailiep@techcrunch.com",
      "phone": "478-588-6896",
      "password": "$2b$10$l9lc0mXS/K.XXto29mWW4OLaTwJuwbnwGkL7dHd35J2rQVk/qjr66"
    },
    {
      "id": 27,
      "name": "Steffen",
      "email": "sjainq@hhs.gov",
      "phone": "414-972-2077",
      "password": "$2b$10$l9lc0mXS/K.XXto29mWW4OLaTwJuwbnwGkL7dHd35J2rQVk/qjr66"
    },
    {
      "id": 28,
      "name": "Quinn",
      "email": "qgreschker@liveinternet.ru",
      "phone": "239-627-8958",
      "password": "$2b$10$l9lc0mXS/K.XXto29mWW4OLaTwJuwbnwGkL7dHd35J2rQVk/qjr66"
    },
    {
      "id": 29,
      "name": "Nicolas",
      "email": "nboijs@linkedin.com",
      "phone": "194-232-2334",
      "password": "$2b$10$l9lc0mXS/K.XXto29mWW4OLaTwJuwbnwGkL7dHd35J2rQVk/qjr66"
    },
    {
      "id": 30,
      "name": "Joy",
      "email": "jyakunint@dell.com",
      "phone": "453-297-9777",
      "password": "$2b$10$l9lc0mXS/K.XXto29mWW4OLaTwJuwbnwGkL7dHd35J2rQVk/qjr66"
    },
    {
      "id": 31,
      "name": "Vilma",
      "email": "vdoorlyu@utexas.edu",
      "phone": "940-300-0672",
      "password": "$2b$10$l9lc0mXS/K.XXto29mWW4OLaTwJuwbnwGkL7dHd35J2rQVk/qjr66"
    },
    {
      "id": 32,
      "name": "Cammy",
      "email": "cdawdaryv@booking.com",
      "phone": "655-167-7361",
      "password": "$2b$10$l9lc0mXS/K.XXto29mWW4OLaTwJuwbnwGkL7dHd35J2rQVk/qjr66"
    },
    {
      "id": 33,
      "name": "Kylynn",
      "email": "kclinew@washingtonpost.com",
      "phone": "199-685-4877",
      "password": "$2b$10$l9lc0mXS/K.XXto29mWW4OLaTwJuwbnwGkL7dHd35J2rQVk/qjr66"
    },
    {
      "id": 34,
      "name": "Timmi",
      "email": "tmumx@naver.com",
      "phone": "198-500-7514",
      "password": "$2b$10$l9lc0mXS/K.XXto29mWW4OLaTwJuwbnwGkL7dHd35J2rQVk/qjr66"
    },
    {
      "id": 35,
      "name": "Fletcher",
      "email": "fdukesburyy@rakuten.co.jp",
      "phone": "113-991-7420",
      "password": "$2b$10$l9lc0mXS/K.XXto29mWW4OLaTwJuwbnwGkL7dHd35J2rQVk/qjr66"
    },
    {
      "id": 36,
      "name": "Marlane",
      "email": "mlemingz@symantec.com",
      "phone": "534-989-2879",
      "password": "$2b$10$l9lc0mXS/K.XXto29mWW4OLaTwJuwbnwGkL7dHd35J2rQVk/qjr66"
    },
    {
      "id": 37,
      "name": "Quinn",
      "email": "qcalles10@parallels.com",
      "phone": "144-999-8941",
      "password": "$2b$10$l9lc0mXS/K.XXto29mWW4OLaTwJuwbnwGkL7dHd35J2rQVk/qjr66"
    },
    {
      "id": 38,
      "name": "Farleigh",
      "email": "fcutmare11@ted.com",
      "phone": "579-239-2246",
      "password": "$2b$10$l9lc0mXS/K.XXto29mWW4OLaTwJuwbnwGkL7dHd35J2rQVk/qjr66"
    },
    {
      "id": 39,
      "name": "Deedee",
      "email": "dhassekl12@vkontakte.ru",
      "phone": "784-608-6484",
      "password": "$2b$10$l9lc0mXS/K.XXto29mWW4OLaTwJuwbnwGkL7dHd35J2rQVk/qjr66"
    },
    {
      "id": 40,
      "name": "Katerina",
      "email": "kriches13@addtoany.com",
      "phone": "385-338-5855",
      "password": "$2b$10$l9lc0mXS/K.XXto29mWW4OLaTwJuwbnwGkL7dHd35J2rQVk/qjr66"
    },
    {
      "id": 41,
      "name": "Bjorn",
      "email": "bpendergast14@fotki.com",
      "phone": "752-244-8196",
      "password": "$2b$10$l9lc0mXS/K.XXto29mWW4OLaTwJuwbnwGkL7dHd35J2rQVk/qjr66"
    },
    {
      "id": 42,
      "name": "Josie",
      "email": "jfrith15@economist.com",
      "phone": "816-461-1901",
      "password": "$2b$10$l9lc0mXS/K.XXto29mWW4OLaTwJuwbnwGkL7dHd35J2rQVk/qjr66"
    },
    {
      "id": 43,
      "name": "Sheilah",
      "email": "springley16@imgur.com",
      "phone": "567-104-0412",
      "password": "$2b$10$l9lc0mXS/K.XXto29mWW4OLaTwJuwbnwGkL7dHd35J2rQVk/qjr66"
    },
    {
      "id": 44,
      "name": "Tabina",
      "email": "twainer17@51.la",
      "phone": "346-197-7354",
      "password": "$2b$10$l9lc0mXS/K.XXto29mWW4OLaTwJuwbnwGkL7dHd35J2rQVk/qjr66"
    },
    {
      "id": 45,
      "name": "Muriel",
      "email": "mdourin18@zdnet.com",
      "phone": "944-509-9721",
      "password": "$2b$10$l9lc0mXS/K.XXto29mWW4OLaTwJuwbnwGkL7dHd35J2rQVk/qjr66"
    },
    {
      "id": 46,
      "name": "Codee",
      "email": "caubry19@ebay.co.uk",
      "phone": "689-765-6087",
      "password": "$2b$10$l9lc0mXS/K.XXto29mWW4OLaTwJuwbnwGkL7dHd35J2rQVk/qjr66"
    },
    {
      "id": 47,
      "name": "Barnie",
      "email": "bdeferraris1a@guardian.co.uk",
      "phone": "922-988-0391",
      "password": "$2b$10$l9lc0mXS/K.XXto29mWW4OLaTwJuwbnwGkL7dHd35J2rQVk/qjr66"
    },
    {
      "id": 48,
      "name": "Rowe",
      "email": "rjedrys1b@psu.edu",
      "phone": "412-205-9718",
      "password": "$2b$10$l9lc0mXS/K.XXto29mWW4OLaTwJuwbnwGkL7dHd35J2rQVk/qjr66"
    },
    {
      "id": 49,
      "name": "Sam",
      "email": "smerwe1c@qq.com",
      "phone": "891-353-9656",
      "password": "$2b$10$l9lc0mXS/K.XXto29mWW4OLaTwJuwbnwGkL7dHd35J2rQVk/qjr66"
    },
    {
      "id": 50,
      "name": "Reilly",
      "email": "rmccaster1d@europa.eu",
      "phone": "871-370-1631",
      "password": "$2b$10$l9lc0mXS/K.XXto29mWW4OLaTwJuwbnwGkL7dHd35J2rQVk/qjr66"
    },
    {
      "id": 51,
      "name": "Lyn",
      "email": "lfish1e@cdc.gov",
      "phone": "610-358-5656",
      "password": "$2b$10$l9lc0mXS/K.XXto29mWW4OLaTwJuwbnwGkL7dHd35J2rQVk/qjr66"
    },
    {
      "id": 52,
      "name": "Jarrod",
      "email": "jbartosik1f@harvard.edu",
      "phone": "160-318-8634",
      "password": "$2b$10$l9lc0mXS/K.XXto29mWW4OLaTwJuwbnwGkL7dHd35J2rQVk/qjr66"
    },
    {
      "id": 53,
      "name": "Shanon",
      "email": "smidlane1g@furl.net",
      "phone": "325-986-8803",
      "password": "$2b$10$l9lc0mXS/K.XXto29mWW4OLaTwJuwbnwGkL7dHd35J2rQVk/qjr66"
    },
    {
      "id": 54,
      "name": "Terrill",
      "email": "tlaban1h@phpbb.com",
      "phone": "172-271-3723",
      "password": "$2b$10$l9lc0mXS/K.XXto29mWW4OLaTwJuwbnwGkL7dHd35J2rQVk/qjr66"
    },
    {
      "id": 55,
      "name": "Sasha",
      "email": "sstaddom1i@desdev.cn",
      "phone": "850-918-6208",
      "password": "$2b$10$l9lc0mXS/K.XXto29mWW4OLaTwJuwbnwGkL7dHd35J2rQVk/qjr66"
    },
    {
      "id": 56,
      "name": "Nichols",
      "email": "nwickham1j@wix.com",
      "phone": "148-162-3468",
      "password": "$2b$10$l9lc0mXS/K.XXto29mWW4OLaTwJuwbnwGkL7dHd35J2rQVk/qjr66"
    },
    {
      "id": 57,
      "name": "Ambrosius",
      "email": "asackur1k@usa.gov",
      "phone": "718-187-0918",
      "password": "$2b$10$l9lc0mXS/K.XXto29mWW4OLaTwJuwbnwGkL7dHd35J2rQVk/qjr66"
    },
    {
      "id": 58,
      "name": "Minni",
      "email": "mschule1l@smugmug.com",
      "phone": "459-913-6985",
      "password": "$2b$10$l9lc0mXS/K.XXto29mWW4OLaTwJuwbnwGkL7dHd35J2rQVk/qjr66"
    },
    {
      "id": 59,
      "name": "Shawna",
      "email": "ssimmance1m@reference.com",
      "phone": "490-770-3643",
      "password": "$2b$10$l9lc0mXS/K.XXto29mWW4OLaTwJuwbnwGkL7dHd35J2rQVk/qjr66"
    },
    {
      "id": 60,
      "name": "Dorian",
      "email": "djuarez1n@behance.net",
      "phone": "796-968-0360",
      "password": "$2b$10$l9lc0mXS/K.XXto29mWW4OLaTwJuwbnwGkL7dHd35J2rQVk/qjr66"
    },
    {
      "id": 61,
      "name": "Vinson",
      "email": "vvenable1o@marriott.com",
      "phone": "651-255-2816",
      "password": "$2b$10$l9lc0mXS/K.XXto29mWW4OLaTwJuwbnwGkL7dHd35J2rQVk/qjr66"
    },
    {
      "id": 62,
      "name": "Lita",
      "email": "lcharlton1p@4shared.com",
      "phone": "407-960-1309",
      "password": "$2b$10$l9lc0mXS/K.XXto29mWW4OLaTwJuwbnwGkL7dHd35J2rQVk/qjr66"
    },
    {
      "id": 63,
      "name": "Francesca",
      "email": "fcowtherd1q@histats.com",
      "phone": "670-123-1462",
      "password": "$2b$10$l9lc0mXS/K.XXto29mWW4OLaTwJuwbnwGkL7dHd35J2rQVk/qjr66"
    },
    {
      "id": 64,
      "name": "Francyne",
      "email": "fsolleme1r@arstechnica.com",
      "phone": "298-156-9362",
      "password": "$2b$10$l9lc0mXS/K.XXto29mWW4OLaTwJuwbnwGkL7dHd35J2rQVk/qjr66"
    },
    {
      "id": 65,
      "name": "Correy",
      "email": "ccromblehome1s@pagesperso-orange.fr",
      "phone": "591-847-3773",
      "password": "$2b$10$l9lc0mXS/K.XXto29mWW4OLaTwJuwbnwGkL7dHd35J2rQVk/qjr66"
    },
    {
      "id": 66,
      "name": "Kata",
      "email": "ksedworth1t@netvibes.com",
      "phone": "283-988-3772",
      "password": "$2b$10$l9lc0mXS/K.XXto29mWW4OLaTwJuwbnwGkL7dHd35J2rQVk/qjr66"
    },
    {
      "id": 67,
      "name": "Paton",
      "email": "pcasterou1u@bloglines.com",
      "phone": "215-118-8092",
      "password": "$2b$10$l9lc0mXS/K.XXto29mWW4OLaTwJuwbnwGkL7dHd35J2rQVk/qjr66"
    },
    {
      "id": 68,
      "name": "Maridel",
      "email": "mtiffney1v@shop-pro.jp",
      "phone": "850-705-6052",
      "password": "$2b$10$l9lc0mXS/K.XXto29mWW4OLaTwJuwbnwGkL7dHd35J2rQVk/qjr66"
    },
    {
      "id": 69,
      "name": "Verile",
      "email": "vloram1w@bravesites.com",
      "phone": "502-320-4060",
      "password": "$2b$10$l9lc0mXS/K.XXto29mWW4OLaTwJuwbnwGkL7dHd35J2rQVk/qjr66"
    },
    {
      "id": 70,
      "name": "Fayina",
      "email": "fcrighton1x@histats.com",
      "phone": "590-453-0991",
      "password": "$2b$10$l9lc0mXS/K.XXto29mWW4OLaTwJuwbnwGkL7dHd35J2rQVk/qjr66"
    },
    {
      "id": 71,
      "name": "Osgood",
      "email": "ovanyutin1y@jugem.jp",
      "phone": "909-156-3216",
      "password": "$2b$10$l9lc0mXS/K.XXto29mWW4OLaTwJuwbnwGkL7dHd35J2rQVk/qjr66"
    },
    {
      "id": 72,
      "name": "Rubina",
      "email": "rcamamill1z@blogger.com",
      "phone": "654-533-9338",
      "password": "$2b$10$l9lc0mXS/K.XXto29mWW4OLaTwJuwbnwGkL7dHd35J2rQVk/qjr66"
    },
    {
      "id": 73,
      "name": "Ruthi",
      "email": "rparadyce20@discovery.com",
      "phone": "357-897-1225",
      "password": "$2b$10$l9lc0mXS/K.XXto29mWW4OLaTwJuwbnwGkL7dHd35J2rQVk/qjr66"
    },
    {
      "id": 74,
      "name": "Didi",
      "email": "drilston21@wikipedia.org",
      "phone": "804-387-8394",
      "password": "$2b$10$l9lc0mXS/K.XXto29mWW4OLaTwJuwbnwGkL7dHd35J2rQVk/qjr66"
    },
    {
      "id": 75,
      "name": "Harmonie",
      "email": "hzambonini22@shinystat.com",
      "phone": "443-246-1179",
      "password": "$2b$10$l9lc0mXS/K.XXto29mWW4OLaTwJuwbnwGkL7dHd35J2rQVk/qjr66"
    },
    {
      "id": 76,
      "name": "Grantley",
      "email": "gbalbeck23@ftc.gov",
      "phone": "254-516-0505",
      "password": "$2b$10$l9lc0mXS/K.XXto29mWW4OLaTwJuwbnwGkL7dHd35J2rQVk/qjr66"
    },
    {
      "id": 77,
      "name": "Merrily",
      "email": "mellingsworth24@lycos.com",
      "phone": "152-283-7976",
      "password": "$2b$10$l9lc0mXS/K.XXto29mWW4OLaTwJuwbnwGkL7dHd35J2rQVk/qjr66"
    },
    {
      "id": 78,
      "name": "Evyn",
      "email": "eryles25@dropbox.com",
      "phone": "468-791-7259",
      "password": "$2b$10$l9lc0mXS/K.XXto29mWW4OLaTwJuwbnwGkL7dHd35J2rQVk/qjr66"
    },
    {
      "id": 79,
      "name": "Nata",
      "email": "nkynan26@vinaora.com",
      "phone": "980-856-1528",
      "password": "$2b$10$l9lc0mXS/K.XXto29mWW4OLaTwJuwbnwGkL7dHd35J2rQVk/qjr66"
    },
    {
      "id": 80,
      "name": "Delinda",
      "email": "ddocker27@uol.com.br",
      "phone": "293-742-2958",
      "password": "$2b$10$l9lc0mXS/K.XXto29mWW4OLaTwJuwbnwGkL7dHd35J2rQVk/qjr66"
    },
    {
      "id": 81,
      "name": "Wang",
      "email": "wgwillym28@huffingtonpost.com",
      "phone": "859-120-5338",
      "password": "$2b$10$l9lc0mXS/K.XXto29mWW4OLaTwJuwbnwGkL7dHd35J2rQVk/qjr66"
    },
    {
      "id": 82,
      "name": "Kimberlyn",
      "email": "kricks29@ycombinator.com",
      "phone": "216-684-5358",
      "password": "$2b$10$l9lc0mXS/K.XXto29mWW4OLaTwJuwbnwGkL7dHd35J2rQVk/qjr66"
    },
    {
      "id": 83,
      "name": "Frank",
      "email": "fantoniewski2a@springer.com",
      "phone": "781-628-1402",
      "password": "$2b$10$l9lc0mXS/K.XXto29mWW4OLaTwJuwbnwGkL7dHd35J2rQVk/qjr66"
    },
    {
      "id": 84,
      "name": "Garnet",
      "email": "gthiese2b@lulu.com",
      "phone": "242-306-6547",
      "password": "$2b$10$l9lc0mXS/K.XXto29mWW4OLaTwJuwbnwGkL7dHd35J2rQVk/qjr66"
    },
    {
      "id": 85,
      "name": "Josiah",
      "email": "jgaenor2c@i2i.jp",
      "phone": "835-175-7601",
      "password": "$2b$10$l9lc0mXS/K.XXto29mWW4OLaTwJuwbnwGkL7dHd35J2rQVk/qjr66"
    },
    {
      "id": 86,
      "name": "Laurette",
      "email": "lsime2d@hatena.ne.jp",
      "phone": "106-109-0201",
      "password": "$2b$10$l9lc0mXS/K.XXto29mWW4OLaTwJuwbnwGkL7dHd35J2rQVk/qjr66"
    },
    {
      "id": 87,
      "name": "Basil",
      "email": "bgroves2e@lulu.com",
      "phone": "410-819-0190",
      "password": "$2b$10$l9lc0mXS/K.XXto29mWW4OLaTwJuwbnwGkL7dHd35J2rQVk/qjr66"
    },
    {
      "id": 88,
      "name": "Courtenay",
      "email": "cconklin2f@cnbc.com",
      "phone": "921-887-2432",
      "password": "$2b$10$l9lc0mXS/K.XXto29mWW4OLaTwJuwbnwGkL7dHd35J2rQVk/qjr66"
    },
    {
      "id": 89,
      "name": "Cam",
      "email": "cprobbing2g@nbcnews.com",
      "phone": "561-983-3474",
      "password": "$2b$10$l9lc0mXS/K.XXto29mWW4OLaTwJuwbnwGkL7dHd35J2rQVk/qjr66"
    },
    {
      "id": 90,
      "name": "Shalom",
      "email": "sshelford2h@phpbb.com",
      "phone": "773-291-0181",
      "password": "$2b$10$l9lc0mXS/K.XXto29mWW4OLaTwJuwbnwGkL7dHd35J2rQVk/qjr66"
    },
    {
      "id": 91,
      "name": "Dag",
      "email": "dhammerstone2i@nps.gov",
      "phone": "622-971-7755",
      "password": "$2b$10$l9lc0mXS/K.XXto29mWW4OLaTwJuwbnwGkL7dHd35J2rQVk/qjr66"
    },
    {
      "id": 92,
      "name": "Yehudi",
      "email": "yconlon2j@paginegialle.it",
      "phone": "669-896-4167",
      "password": "$2b$10$l9lc0mXS/K.XXto29mWW4OLaTwJuwbnwGkL7dHd35J2rQVk/qjr66"
    },
    {
      "id": 93,
      "name": "Osmund",
      "email": "olyttle2k@merriam-webster.com",
      "phone": "713-551-5810",
      "password": "$2b$10$l9lc0mXS/K.XXto29mWW4OLaTwJuwbnwGkL7dHd35J2rQVk/qjr66"
    },
    {
      "id": 94,
      "name": "Gottfried",
      "email": "gfealy2l@wsj.com",
      "phone": "732-604-3992",
      "password": "$2b$10$l9lc0mXS/K.XXto29mWW4OLaTwJuwbnwGkL7dHd35J2rQVk/qjr66"
    },
    {
      "id": 95,
      "name": "Sibilla",
      "email": "sarrigucci2m@cdc.gov",
      "phone": "762-736-3207",
      "password": "$2b$10$l9lc0mXS/K.XXto29mWW4OLaTwJuwbnwGkL7dHd35J2rQVk/qjr66"
    },
    {
      "id": 96,
      "name": "Alexandrina",
      "email": "arushton2n@foxnews.com",
      "phone": "588-167-8984",
      "password": "$2b$10$l9lc0mXS/K.XXto29mWW4OLaTwJuwbnwGkL7dHd35J2rQVk/qjr66"
    },
    {
      "id": 97,
      "name": "Jamison",
      "email": "jwolfe2o@comcast.net",
      "phone": "875-261-4538",
      "password": "$2b$10$l9lc0mXS/K.XXto29mWW4OLaTwJuwbnwGkL7dHd35J2rQVk/qjr66"
    },
    {
      "id": 98,
      "name": "Fianna",
      "email": "fnolin2p@wikimedia.org",
      "phone": "813-588-8673",
      "password": "$2b$10$l9lc0mXS/K.XXto29mWW4OLaTwJuwbnwGkL7dHd35J2rQVk/qjr66"
    },
    {
      "id": 99,
      "name": "Rik",
      "email": "rgallety2q@vistaprint.com",
      "phone": "256-919-8225",
      "password": "$2b$10$l9lc0mXS/K.XXto29mWW4OLaTwJuwbnwGkL7dHd35J2rQVk/qjr66"
    },
    {
      "id": 100,
      "name": "Thornie",
      "email": "tsargant2r@webnode.com",
      "phone": "614-657-7849",
      "password": "$2b$10$l9lc0mXS/K.XXto29mWW4OLaTwJuwbnwGkL7dHd35J2rQVk/qjr66"
    },
    {
      "name": "Nguyen Thi Thuy Van",
      "email": "b@gmail.com",
      "phone": "0987654321",
      "isAdmin": false,
      "id": "R1U6c73Xq"
    }
  ],
  "transactions": [
    {
      "userId": "vQwbCqEBl",
      "bookId": "Yi5xEFvco",
      "id": "8gR2e6e33",
      "isComplete": true
    },
    {
      "userId": "81fugC_nl",
      "bookId": "ZQnh2SCCn",
      "id": "x3BwGE31_",
      "isComplete": true
    },
    {
      "userId": "vQwbCqEBl",
      "bookId": "ZQnh2SCCn",
      "id": "3TYAM96Zo",
      "isComplete": true
    },
    {
      "userId": "vQwbCqEBl",
      "bookId": "Yi5xEFvco",
      "id": "3O3vW74XX",
      "isComplete": true
    },
    {
      "userId": "vQwbCqEBl",
      "bookId": "Yi5xEFvco",
      "id": "c4wuVNizNw",
      "isComplete": false
    },
    {
      "userId": "vQwbCqEBl",
      "bookId": "Yi5xEFvco",
      "id": "E8-kWlBP0d",
      "isComplete": false
    },
    {
      "id": 1,
      "bookId": "Yi5xEFvco",
      "userId": 1,
      "isComplete": false
    },
    {
      "id": 2,
      "bookId": "Yi5xEFvco",
      "userId": 2,
      "isComplete": true
    },
    {
      "id": 3,
      "bookId": "ZQnh2SCCn",
      "userId": 3,
      "isComplete": true
    },
    {
      "id": 4,
      "bookId": "Yi5xEFvco",
      "userId": 4,
      "isComplete": false
    },
    {
      "id": 5,
      "bookId": "ZQnh2SCCn",
      "userId": 5,
      "isComplete": false
    },
    {
      "id": 6,
      "bookId": "Yi5xEFvco",
      "userId": 6,
      "isComplete": true
    },
    {
      "id": 7,
      "bookId": "Yi5xEFvco",
      "userId": 7,
      "isComplete": true
    },
    {
      "id": 8,
      "bookId": "ZQnh2SCCn",
      "userId": 8,
      "isComplete": false
    },
    {
      "id": 9,
      "bookId": "ZQnh2SCCn",
      "userId": 9,
      "isComplete": true
    },
    {
      "id": 10,
      "bookId": "ZQnh2SCCn",
      "userId": 10,
      "isComplete": false
    },
    {
      "id": 11,
      "bookId": "ZQnh2SCCn",
      "userId": 11,
      "isComplete": true
    },
    {
      "id": 12,
      "bookId": "ZQnh2SCCn",
      "userId": 12,
      "isComplete": true
    },
    {
      "id": 13,
      "bookId": "ZQnh2SCCn",
      "userId": 13,
      "isComplete": false
    },
    {
      "id": 14,
      "bookId": "ZQnh2SCCn",
      "userId": 14,
      "isComplete": true
    },
    {
      "id": 15,
      "bookId": "Yi5xEFvco",
      "userId": 15,
      "isComplete": false
    },
    {
      "id": 16,
      "bookId": "ZQnh2SCCn",
      "userId": 16,
      "isComplete": true
    },
    {
      "id": 17,
      "bookId": "Yi5xEFvco",
      "userId": 17,
      "isComplete": true
    },
    {
      "id": 18,
      "bookId": "ZQnh2SCCn",
      "userId": 18,
      "isComplete": false
    },
    {
      "id": 19,
      "bookId": "Yi5xEFvco",
      "userId": 19,
      "isComplete": false
    },
    {
      "id": 20,
      "bookId": "Yi5xEFvco",
      "userId": 20,
      "isComplete": false
    },
    {
      "id": 21,
      "bookId": "ZQnh2SCCn",
      "userId": 21,
      "isComplete": true
    },
    {
      "id": 22,
      "bookId": "Yi5xEFvco",
      "userId": 22,
      "isComplete": false
    },
    {
      "id": 23,
      "bookId": "Yi5xEFvco",
      "userId": 23,
      "isComplete": true
    },
    {
      "id": 24,
      "bookId": "ZQnh2SCCn",
      "userId": 24,
      "isComplete": false
    },
    {
      "id": 25,
      "bookId": "Yi5xEFvco",
      "userId": 25,
      "isComplete": false
    },
    {
      "id": 26,
      "bookId": "ZQnh2SCCn",
      "userId": 26,
      "isComplete": true
    },
    {
      "id": 27,
      "bookId": "ZQnh2SCCn",
      "userId": 27,
      "isComplete": true
    },
    {
      "id": 28,
      "bookId": "Yi5xEFvco",
      "userId": 28,
      "isComplete": true
    },
    {
      "id": 29,
      "bookId": "Yi5xEFvco",
      "userId": 29,
      "isComplete": false
    },
    {
      "id": 30,
      "bookId": "Yi5xEFvco",
      "userId": 30,
      "isComplete": true
    },
    {
      "id": 31,
      "bookId": "Yi5xEFvco",
      "userId": 31,
      "isComplete": false
    },
    {
      "id": 32,
      "bookId": "Yi5xEFvco",
      "userId": 32,
      "isComplete": true
    },
    {
      "id": 33,
      "bookId": "ZQnh2SCCn",
      "userId": 33,
      "isComplete": true
    },
    {
      "id": 34,
      "bookId": "Yi5xEFvco",
      "userId": 34,
      "isComplete": true
    },
    {
      "id": 35,
      "bookId": "ZQnh2SCCn",
      "userId": 35,
      "isComplete": true
    },
    {
      "id": 36,
      "bookId": "Yi5xEFvco",
      "userId": 36,
      "isComplete": false
    },
    {
      "id": 37,
      "bookId": "Yi5xEFvco",
      "userId": 37,
      "isComplete": true
    },
    {
      "id": 38,
      "bookId": "ZQnh2SCCn",
      "userId": 38,
      "isComplete": false
    },
    {
      "id": 39,
      "bookId": "Yi5xEFvco",
      "userId": 39,
      "isComplete": false
    },
    {
      "id": 40,
      "bookId": "ZQnh2SCCn",
      "userId": 40,
      "isComplete": true
    },
    {
      "id": 41,
      "bookId": "Yi5xEFvco",
      "userId": 41,
      "isComplete": false
    },
    {
      "id": 42,
      "bookId": "Yi5xEFvco",
      "userId": 42,
      "isComplete": true
    },
    {
      "id": 43,
      "bookId": "Yi5xEFvco",
      "userId": 43,
      "isComplete": true
    },
    {
      "id": 44,
      "bookId": "ZQnh2SCCn",
      "userId": 44,
      "isComplete": false
    },
    {
      "id": 45,
      "bookId": "Yi5xEFvco",
      "userId": 45,
      "isComplete": false
    },
    {
      "id": 46,
      "bookId": "ZQnh2SCCn",
      "userId": 46,
      "isComplete": true
    },
    {
      "id": 47,
      "bookId": "ZQnh2SCCn",
      "userId": 47,
      "isComplete": true
    },
    {
      "id": 48,
      "bookId": "Yi5xEFvco",
      "userId": 48,
      "isComplete": false
    },
    {
      "id": 49,
      "bookId": "ZQnh2SCCn",
      "userId": 49,
      "isComplete": false
    },
    {
      "id": 50,
      "bookId": "Yi5xEFvco",
      "userId": 50,
      "isComplete": true
    },
    {
      "id": 51,
      "bookId": "ZQnh2SCCn",
      "userId": 51,
      "isComplete": false
    },
    {
      "id": 52,
      "bookId": "Yi5xEFvco",
      "userId": 52,
      "isComplete": false
    },
    {
      "id": 53,
      "bookId": "Yi5xEFvco",
      "userId": 53,
      "isComplete": true
    },
    {
      "id": 54,
      "bookId": "ZQnh2SCCn",
      "userId": 54,
      "isComplete": true
    },
    {
      "id": 55,
      "bookId": "ZQnh2SCCn",
      "userId": 55,
      "isComplete": false
    },
    {
      "id": 56,
      "bookId": "Yi5xEFvco",
      "userId": 56,
      "isComplete": true
    },
    {
      "id": 57,
      "bookId": "ZQnh2SCCn",
      "userId": 57,
      "isComplete": true
    },
    {
      "id": 58,
      "bookId": "Yi5xEFvco",
      "userId": 58,
      "isComplete": false
    },
    {
      "id": 59,
      "bookId": "ZQnh2SCCn",
      "userId": 59,
      "isComplete": true
    },
    {
      "id": 60,
      "bookId": "ZQnh2SCCn",
      "userId": 60,
      "isComplete": true
    },
    {
      "id": 61,
      "bookId": "Yi5xEFvco",
      "userId": 61,
      "isComplete": false
    },
    {
      "id": 62,
      "bookId": "Yi5xEFvco",
      "userId": 62,
      "isComplete": true
    },
    {
      "id": 63,
      "bookId": "Yi5xEFvco",
      "userId": 63,
      "isComplete": false
    },
    {
      "id": 64,
      "bookId": "ZQnh2SCCn",
      "userId": 64,
      "isComplete": true
    },
    {
      "id": 65,
      "bookId": "Yi5xEFvco",
      "userId": 65,
      "isComplete": false
    },
    {
      "id": 66,
      "bookId": "ZQnh2SCCn",
      "userId": 66,
      "isComplete": true
    },
    {
      "id": 67,
      "bookId": "ZQnh2SCCn",
      "userId": 67,
      "isComplete": false
    },
    {
      "id": 68,
      "bookId": "Yi5xEFvco",
      "userId": 68,
      "isComplete": false
    },
    {
      "id": 69,
      "bookId": "Yi5xEFvco",
      "userId": 69,
      "isComplete": false
    },
    {
      "id": 70,
      "bookId": "ZQnh2SCCn",
      "userId": 70,
      "isComplete": true
    },
    {
      "id": 71,
      "bookId": "ZQnh2SCCn",
      "userId": 71,
      "isComplete": false
    },
    {
      "id": 72,
      "bookId": "ZQnh2SCCn",
      "userId": 72,
      "isComplete": true
    },
    {
      "id": 73,
      "bookId": "ZQnh2SCCn",
      "userId": 73,
      "isComplete": false
    },
    {
      "id": 74,
      "bookId": "ZQnh2SCCn",
      "userId": 74,
      "isComplete": false
    },
    {
      "id": 75,
      "bookId": "ZQnh2SCCn",
      "userId": 75,
      "isComplete": true
    },
    {
      "id": 76,
      "bookId": "ZQnh2SCCn",
      "userId": 76,
      "isComplete": false
    },
    {
      "id": 77,
      "bookId": "Yi5xEFvco",
      "userId": 77,
      "isComplete": false
    },
    {
      "id": 78,
      "bookId": "Yi5xEFvco",
      "userId": 78,
      "isComplete": false
    },
    {
      "id": 79,
      "bookId": "Yi5xEFvco",
      "userId": 79,
      "isComplete": false
    },
    {
      "id": 80,
      "bookId": "Yi5xEFvco",
      "userId": 80,
      "isComplete": false
    },
    {
      "id": 81,
      "bookId": "ZQnh2SCCn",
      "userId": 81,
      "isComplete": true
    },
    {
      "id": 82,
      "bookId": "Yi5xEFvco",
      "userId": 82,
      "isComplete": true
    },
    {
      "id": 83,
      "bookId": "Yi5xEFvco",
      "userId": 83,
      "isComplete": true
    },
    {
      "id": 84,
      "bookId": "ZQnh2SCCn",
      "userId": 84,
      "isComplete": false
    },
    {
      "id": 85,
      "bookId": "ZQnh2SCCn",
      "userId": 85,
      "isComplete": false
    },
    {
      "id": 86,
      "bookId": "ZQnh2SCCn",
      "userId": 86,
      "isComplete": false
    },
    {
      "id": 87,
      "bookId": "Yi5xEFvco",
      "userId": 87,
      "isComplete": true
    },
    {
      "id": 88,
      "bookId": "ZQnh2SCCn",
      "userId": 88,
      "isComplete": true
    },
    {
      "id": 89,
      "bookId": "Yi5xEFvco",
      "userId": 89,
      "isComplete": false
    },
    {
      "id": 90,
      "bookId": "Yi5xEFvco",
      "userId": 90,
      "isComplete": true
    },
    {
      "id": 91,
      "bookId": "ZQnh2SCCn",
      "userId": 91,
      "isComplete": false
    },
    {
      "id": 92,
      "bookId": "Yi5xEFvco",
      "userId": 92,
      "isComplete": true
    },
    {
      "id": 93,
      "bookId": "ZQnh2SCCn",
      "userId": 93,
      "isComplete": true
    },
    {
      "id": 94,
      "bookId": "ZQnh2SCCn",
      "userId": 94,
      "isComplete": false
    },
    {
      "id": 95,
      "bookId": "ZQnh2SCCn",
      "userId": 95,
      "isComplete": false
    },
    {
      "id": 96,
      "bookId": "ZQnh2SCCn",
      "userId": 96,
      "isComplete": true
    },
    {
      "id": 97,
      "bookId": "ZQnh2SCCn",
      "userId": 97,
      "isComplete": false
    },
    {
      "id": 98,
      "bookId": "ZQnh2SCCn",
      "userId": 98,
      "isComplete": false
    },
    {
      "id": 99,
      "bookId": "ZQnh2SCCn",
      "userId": 99,
      "isComplete": false
    },
    {
      "id": 100,
      "bookId": "Yi5xEFvco",
      "userId": 100,
      "isComplete": true
    },
    {
      "userId": "81fugC_nl",
      "id": "VyPTWW5JoX",
      "isComplete": false,
      "bookId": "Gb5j6TLyk"
    },
    {
      "userId": "81fugC_nl",
      "id": "VyPTWW5JoX",
      "isComplete": false,
      "bookId": "Gb5j6TLyk"
    },
    {
      "userId": "81fugC_nl",
      "id": "JmS1TtUyvg",
      "isComplete": false,
      "bookId": "Gb5j6TLyk"
    },
    {
      "userId": "81fugC_nl",
      "id": "JmS1TtUyvg",
      "isComplete": false,
      "bookId": "Gb5j6TLyk"
    },
    {
      "userId": "81fugC_nl",
      "id": "Yiji8hx2ea",
      "isComplete": false,
      "bookId": "ZQnh2SCCn"
    },
    {
      "userId": "81fugC_nl",
      "id": "Yiji8hx2ea",
      "isComplete": false,
      "bookId": "ZQnh2SCCn"
    },
    {
      "userId": "RSpOpAkTn",
      "id": "0EjcthCOqi",
      "isComplete": false,
      "bookId": "ZQnh2SCCn"
    },
    {
      "userId": "RSpOpAkTn",
      "id": "0EjcthCOqi",
      "isComplete": false,
      "bookId": "ZQnh2SCCn"
    },
    {
      "userId": "vQwbCqEBl",
      "id": "PQqD6KvVW",
      "isComplete": false,
      "bookId": "Yi5xEFvco"
    },
    {
      "userId": "vQwbCqEBl",
      "id": "M-VQdSgz6",
      "isComplete": false,
      "bookId": "Yi5xEFvco"
    }
  ],
  "sessions": [
    {
      "id": "-kZMpl_ZS"
    },
    {},
    {
      "id": "cxjqQSjf6"
    },
    {},
    {
      "id": "mzm2FT9eD"
    },
    {},
    {},
    {
      "id": "JQkK8e1ym"
    },
    {},
    {},
    {
      "id": "9eEILTE-E"
    },
    {},
    {
      "id": "SLSkPXW1m"
    },
    {},
    {},
    {},
    {},
    {},
    {},
    {},
    {
      "id": "X_cYgq8Va"
    },
    {},
    {
      "id": "RXHcXpn0F"
    },
    {},
    {
      "id": "kYHdEhPyE"
    },
    {},
    {
      "id": "AvYb9P90R"
    },
    {},
    {
      "id": "vhqltW4Tu"
    },
    {},
    {},
    {
      "id": "puvw8GUg_"
    },
    {},
    {
      "id": "woc0ysEPM"
    },
    {},
    {},
    {},
    {},
    {
      "id": "nlEPzuDsn"
    },
    {},
    {
      "id": "0xwoP9rBD"
    },
    {},
    {
      "id": "zsMbSFG1h"
    },
    {},
    {
      "id": "_M2-yvkKo"
    },
    {},
    {},
    {
      "id": "JbdEKqeio"
    },
    {
      "id": "Y7GncxXhw"
    },
    {},
    {},
    {
      "id": "axIk4KmIZ"
    },
    {},
    {
      "id": "ZEAJYb0ZW"
    },
    {},
    {
      "id": "Kff_M3jWN"
    },
    {},
    {},
    {},
    {},
    {},
    {},
    {},
    {
      "id": "wmfqSrkBl"
    },
    {},
    {
      "id": "ow0_vzSaC"
    },
    {},
    {
      "id": "mn_v_4ubQ"
    },
    {},
    {},
    {
      "id": "08_Sv2QTx"
    },
    {},
    {},
    {},
    {},
    {},
    {
      "id": "1wtOn_gy1"
    },
    {},
    {
      "id": "8pMlGT3Ae"
    },
    {},
    {
      "id": "Cq2zSO_qu"
    },
    {},
    {
      "id": "Hxtx74qRf"
    },
    {},
    {
      "id": "i_dv-Iy45"
    },
    {},
    {},
    {
      "id": "tQyo0Uzxm"
    },
    {},
    {},
    {
      "id": "XXY9x3fHx"
    },
    {},
    {
      "id": "KjxfFpF4f"
    },
    {},
    {
      "id": "oyRhOOK_Z"
    },
    {},
    {},
    {},
    {},
    {},
    {},
    {},
    {},
    {},
    {
      "id": "fg6faaqBf"
    },
    {},
    {
      "id": "3YuJFq-Fu"
    },
    {},
    {
      "id": "6NBVhWYPQ"
    },
    {},
    {},
    {
      "id": "OyIsw0VgW"
    },
    {},
    {
      "id": "0C7KBxzE6"
    },
    {},
    {
      "id": "z50nL4jMa"
    },
    {},
    {
      "id": "aJIonTJIO"
    },
    {},
    {
      "id": "Zl7g93Wg5"
    },
    {},
    {
      "id": "BbJ9il-ZU"
    },
    {},
    {},
    {
      "id": "_v-V_-T32"
    },
    {},
    {},
    {},
    {
      "id": "GsnwfgRPi"
    },
    {},
    {},
    {
      "id": "Zl4RASPSp"
    },
    {},
    {
      "id": "mvpzzm-LX"
    },
    {},
    {
      "id": "bGau5KEfj"
    },
    {},
    {
      "id": "6uyIGKKXj"
    },
    {},
    {
      "id": "aB_wYown9"
    },
    {},
    {
      "id": "Ih5HEzvor"
    },
    {},
    {},
    {
      "id": "Cn4EFX5ts"
    },
    {},
    {},
    {
      "id": "IZrvAoYQ7"
    },
    {},
    {
      "id": "iIbmJbgH_"
    },
    {},
    {
      "id": "dqao0Yrtv"
    },
    {},
    {
      "id": "O-u9B2abL"
    },
    {},
    {
      "id": "irvXUamaT"
    },
    {},
    {
      "id": "Cj_9lRkpp"
    },
    {},
    {},
    {
      "id": "Cy7ZIqyqC"
    },
    {},
    {},
    {
      "id": "qFSQb6Y7J"
    },
    {},
    {},
    {},
    {
      "id": "6UEvEmAF7"
    },
    {},
    {},
    {
      "id": "DZitOGZYo"
    },
    {},
    {
      "id": "JBu0BzPJs"
    },
    {},
    {
      "id": "ODm8KhuYD"
    },
    {},
    {},
    {
      "id": "2KPEuXGix"
    },
    {},
    {},
    {},
    {
      "id": "K3BcaHhk8"
    },
    {},
    {
      "id": "7JaCIr9zd"
    },
    {
      "id": "pWzllWijK"
    },
    {},
    {},
    {},
    {
      "id": "G338077kZ"
    },
    {},
    {},
    {},
    {},
    {},
    {
      "id": "-xCLLegg4"
    },
    {},
    {},
    {},
    {},
    {},
    {},
    {},
    {},
    {
      "id": "hazr1G5bX"
    },
    {
      "id": "AtbRb8eA28"
    },
    {},
    {},
    {
      "id": "UCKmPAEro"
    },
    {},
    {},
    {},
    {},
    {
      "id": "QPhRnTHgh"
    },
    {},
    {
      "id": "n8QaKv7pF"
    },
    {},
    {
      "id": "ABYhsuDWv"
    },
    {},
    {
      "id": "9SfWvigEP"
    },
    {},
    {},
    {},
    {
      "id": "hib_cF_rB"
    },
    {},
    {
      "id": "bLz04-zZR"
    },
    {},
    {},
    {},
    {},
    {},
    {},
    {},
    {},
    {},
    {
      "id": "8hC8Gc-gr"
    }
  ]
}